{
  "slices": {
    "__TYPE__": "SliceContentType",
    "value": [
      {
        "key": "hero$00058d4f-dbd1-4668-aa89-59c0842a33ea",
        "name": "hero",
        "widget": {
          "__TYPE__": "SharedSliceContent",
          "variation": "default",
          "primary": {
            "title": {
              "__TYPE__": "StructuredTextContent",
              "value": [
                {
                  "type": "heading1",
                  "content": {
                    "text": "Government"
                  }
                }
              ]
            },
            "description": {
              "__TYPE__": "StructuredTextContent",
              "value": [
                {
                  "type": "paragraph",
                  "content": {
                    "text": "Anim id ut esse excepteur esse nostrud dolore voluptate esse. Ex Lorem elit enim fugiat ut esse mollit culpa sit sunt irure."
                  }
                }
              ]
            },
            "image": {
              "__TYPE__": "ImageContent",
              "origin": {
                "id": "main",
                "url": "https://images.unsplash.com/photo-1576662712957-9c79ae1280f8",
                "width": 3456,
                "height": 3456
              },
              "url": "https://images.unsplash.com/photo-1576662712957-9c79ae1280f8",
              "width": 3456,
              "height": 3456,
              "edit": {
                "zoom": 1,
                "crop": {
                  "x": 0,
                  "y": 0
                },
                "background": "transparent"
              },
              "thumbnails": {}
            }
          },
          "items": [
            {
              "__TYPE__": "GroupItemContent",
              "value": []
            }
          ]
        }
      }
    ]
  }
}